ragulate/__init__.py
ragulate/analysis.py
ragulate/cli.py
ragulate/data.py
ragulate/debug.py
ragulate/framework.py
ragulate/logging_config.py
ragulate/utils.py
ragulate/cli_commands/__init__.py
ragulate/cli_commands/compare.py
ragulate/cli_commands/debug.py
ragulate/cli_commands/download.py
ragulate/cli_commands/ingest.py
ragulate/cli_commands/query.py
ragulate/cli_commands/run.py
ragulate/cli_commands/utils.py
ragulate/config/__init__.py
ragulate/config/base_config_schema.py
ragulate/config/config_parser.py
ragulate/config/config_schema_0_1.py
ragulate/config/objects.py
ragulate/config/utils.py
ragulate/datasets/__init__.py
ragulate/datasets/base_dataset.py
ragulate/datasets/crag_dataset.py
ragulate/datasets/llama_dataset.py
ragulate/datasets/test_dataset.py
ragulate/datasets/utils.py
ragulate/pipelines/__init__.py
ragulate/pipelines/base_pipeline.py
ragulate/pipelines/feedbacks.py
ragulate/pipelines/ingest_pipeline.py
ragulate/pipelines/query_pipeline.py
ragulate/ui/__init__.py
ragulate/ui/column.py
ragulate/ui/home.py
ragulate/ui/launcher.py
ragulate/ui/state.py
ragulate/ui/utils.py
ragulate/ui/pages/chart.py
ragulate/ui/pages/compare.py
ragulate/ui/pages/filter.py
ragulate-0.0.14.dist-info/METADATA
ragulate-0.0.14.dist-info/WHEEL
ragulate-0.0.14.dist-info/entry_points.txt
ragulate-0.0.14.dist-info/licenses/LICENSE
ragulate-0.0.14.dist-info/RECORD
