Metadata-Version: 2.3
Name: ragulate
Version: 0.0.14
Summary: A tool for evaluating RAG pipelines
Project-URL: Homepage, https://pypi.org/project/ragulate/
Project-URL: Repository, https://github.com/datastax/ragulate.git
Project-URL: Issues, https://github.com/datastax/ragulate/issues
Author-email: Eric Pinzur <eric.pinzur@datastax.com>
Maintainer: Datastax
License:                                  Apache License
License-File: LICENSE
Requires-Python: >=3.10
Requires-Dist: aiofiles>=24.1.0
Requires-Dist: cerberus>=1.3.5
Requires-Dist: inflection>=0.5.1
Requires-Dist: kaleido>=0.2.1
Requires-Dist: llama-index-core==0.10.31
Requires-Dist: llama-index==0.10.31
Requires-Dist: nltk==3.8.1
Requires-Dist: numpy>=1.23.5
Requires-Dist: pandas>=2.2.2
Requires-Dist: plotly>=5.23.0
Requires-Dist: pydantic~=2.7.4
Requires-Dist: python-dotenv>=1.0.1
Requires-Dist: pyyaml>=6.0.2
Requires-Dist: seaborn>=0.13.2
Requires-Dist: tqdm>=4.66.5
Requires-Dist: trulens-eval==0.33.0
Requires-Dist: typing-extensions==4.12.2
Requires-Dist: watchdog>=4.0.2
